celloracle/__init__.py
celloracle/helpers.py
celloracle/version.py
celloracle/data/__init__.py
celloracle/data/config.py
celloracle/data/load_data.py
celloracle/data/load_promoter_base_GRN.py
celloracle/motif_analysis/__init__.py
celloracle/motif_analysis/motif_analysis_utility.py
celloracle/motif_analysis/motif_data.py
celloracle/motif_analysis/process_bed_file.py
celloracle/motif_analysis/process_cicero_data.py
celloracle/motif_analysis/reference_genomes.py
celloracle/motif_analysis/tfinfo_core.py
celloracle/motif_analysis/tss_annotation.py
celloracle/motif_analysis/tss_ref_data/AmexG_v6.0-DD_tss_info.bed
celloracle/motif_analysis/tss_ref_data/Cavpor3.0_tss_info.bed
celloracle/motif_analysis/tss_ref_data/Sscrofa11.1_tss_info.bed
celloracle/motif_analysis/tss_ref_data/TAIR10_tss_info.bed
celloracle/motif_analysis/tss_ref_data/Xenopus_laevis_v10.1_tss_info.bed
celloracle/motif_analysis/tss_ref_data/ce10_tss_info.bed
celloracle/motif_analysis/tss_ref_data/ce6_tss_info.bed
celloracle/motif_analysis/tss_ref_data/danRer10_tss_info.bed
celloracle/motif_analysis/tss_ref_data/danRer11_tss_info.bed
celloracle/motif_analysis/tss_ref_data/danRer7_tss_info.bed
celloracle/motif_analysis/tss_ref_data/dm3_tss_info.bed
celloracle/motif_analysis/tss_ref_data/dm6_tss_info.bed
celloracle/motif_analysis/tss_ref_data/galGal4_tss_info.bed
celloracle/motif_analysis/tss_ref_data/galGal5_tss_info.bed
celloracle/motif_analysis/tss_ref_data/galGal6_tss_info.bed
celloracle/motif_analysis/tss_ref_data/hg19_tss_info.bed
celloracle/motif_analysis/tss_ref_data/hg38_tss_info.bed
celloracle/motif_analysis/tss_ref_data/mm10_tss_info.bed
celloracle/motif_analysis/tss_ref_data/mm39_tss_info.bed
celloracle/motif_analysis/tss_ref_data/mm9_tss_info.bed
celloracle/motif_analysis/tss_ref_data/rn4_tss_info.bed
celloracle/motif_analysis/tss_ref_data/rn5_tss_info.bed
celloracle/motif_analysis/tss_ref_data/rn6_tss_info.bed
celloracle/motif_analysis/tss_ref_data/sacCer2_tss_info.bed
celloracle_lite-0.22.0.dist-info/licenses/LICENSE
celloracle_lite-0.22.0.dist-info/METADATA
celloracle_lite-0.22.0.dist-info/WHEEL
celloracle_lite-0.22.0.dist-info/entry_points.txt
celloracle_lite-0.22.0.dist-info/top_level.txt
celloracle_lite-0.22.0.dist-info/RECORD
