Metadata-Version: 2.4
Name: celloracle-lite
Version: 0.22.0
Summary: Lightweight fork of CellOracle for GRN analysis with reduced dependencies
Author-email: Kenji Kamimoto <kamimoto@wustl.edu>
Maintainer: cantinilab
License: Apache-2.0 (modified; non-commercial academic use only)
Project-URL: Homepage, https://github.com/morris-lab/CellOracle
Project-URL: Fork Repository, https://github.com/cantinilab/celloracle
Keywords: scRNA-seq,GRN,simulation,gene perturbation,celloracle-lite
Classifier: Development Status :: 4 - Beta
Classifier: Intended Audience :: Science/Research
Classifier: Intended Audience :: Developers
Classifier: Topic :: Scientific/Engineering :: Bio-Informatics
Classifier: Programming Language :: Python :: 3.6
Classifier: Programming Language :: Python :: 3.7
Classifier: Programming Language :: Python :: 3.8
Classifier: Programming Language :: Python :: 3.10
Requires-Python: >=3.6
License-File: LICENSE
Requires-Dist: numpy==1.26.4
Requires-Dist: scipy
Requires-Dist: cython
Requires-Dist: numba>=0.50.1
Requires-Dist: scikit-learn
Requires-Dist: pandas
Requires-Dist: tqdm>=4.45
Requires-Dist: IPython
Requires-Dist: anndata<=0.10.8,>=0.7.5
Requires-Dist: scanpy>=1.6
Requires-Dist: joblib
Requires-Dist: genomepy>=0.8.4
Requires-Dist: gimmemotifs<=0.18.2,>=0.14.4
Requires-Dist: statsmodels==0.14.5
Dynamic: license-file
